jupyterlab_mosaic/__init__.py
jupyterlab_mosaic/_version.py
jupyterlab_mosaic/labextension/package.json
jupyterlab_mosaic/labextension/static/715.4914ed1903d19da69771.js
jupyterlab_mosaic/labextension/static/747.cbe0483053be2142aac4.js
jupyterlab_mosaic/labextension/static/remoteEntry.bbc2084b8218ab2ca3d2.js
jupyterlab_mosaic/labextension/static/style.js
jupyterlab_mosaic/labextension/static/third-party-licenses.json
jupyterlab_mosaic-0.1.1.data/data/share/jupyter/labextensions/jupyterlab-mosaic/install.json
jupyterlab_mosaic-0.1.1.data/data/share/jupyter/labextensions/jupyterlab-mosaic/package.json
jupyterlab_mosaic-0.1.1.data/data/share/jupyter/labextensions/jupyterlab-mosaic/static/715.4914ed1903d19da69771.js
jupyterlab_mosaic-0.1.1.data/data/share/jupyter/labextensions/jupyterlab-mosaic/static/747.cbe0483053be2142aac4.js
jupyterlab_mosaic-0.1.1.data/data/share/jupyter/labextensions/jupyterlab-mosaic/static/remoteEntry.bbc2084b8218ab2ca3d2.js
jupyterlab_mosaic-0.1.1.data/data/share/jupyter/labextensions/jupyterlab-mosaic/static/style.js
jupyterlab_mosaic-0.1.1.data/data/share/jupyter/labextensions/jupyterlab-mosaic/static/third-party-licenses.json
jupyterlab_mosaic-0.1.1.dist-info/LICENSE
jupyterlab_mosaic-0.1.1.dist-info/METADATA
jupyterlab_mosaic-0.1.1.dist-info/WHEEL
jupyterlab_mosaic-0.1.1.dist-info/top_level.txt
jupyterlab_mosaic-0.1.1.dist-info/RECORD
